odoo8_addon_l10n_it_fiscal_payment_term-8.0.1.0.0-nspkg.pth
odoo_addons/l10n_it_fiscal_payment_term/README.rst
odoo_addons/l10n_it_fiscal_payment_term/__init__.py
odoo_addons/l10n_it_fiscal_payment_term/__openerp__.py
odoo_addons/l10n_it_fiscal_payment_term/data/fatturapa_data.xml
odoo_addons/l10n_it_fiscal_payment_term/i18n/it.po
odoo_addons/l10n_it_fiscal_payment_term/i18n/l10n_it_fiscal_payment_term.pot
odoo_addons/l10n_it_fiscal_payment_term/models/__init__.py
odoo_addons/l10n_it_fiscal_payment_term/models/account.py
odoo_addons/l10n_it_fiscal_payment_term/security/ir.model.access.csv
odoo_addons/l10n_it_fiscal_payment_term/static/description/icon.png
odoo_addons/l10n_it_fiscal_payment_term/views/account_view.xml
odoo8_addon_l10n_it_fiscal_payment_term-8.0.1.0.0.dist-info/METADATA
odoo8_addon_l10n_it_fiscal_payment_term-8.0.1.0.0.dist-info/WHEEL
odoo8_addon_l10n_it_fiscal_payment_term-8.0.1.0.0.dist-info/namespace_packages.txt
odoo8_addon_l10n_it_fiscal_payment_term-8.0.1.0.0.dist-info/top_level.txt
odoo8_addon_l10n_it_fiscal_payment_term-8.0.1.0.0.dist-info/RECORD
