Metadata-Version: 2.1
Name: odoo8-addon-l10n-it-fiscal-payment-term
Version: 8.0.1.0.0
Summary: Electronic invoices payment
Home-page: https://odoo-community.org
Author: Davide Corio, Agile Business Group, Innoviu, Odoo Italia Network, Gianmarco Conte, Odoo Community Association (OCA)
Author-email: support@odoo-community.org
License: LGPL-3
Platform: UNKNOWN
Classifier: Programming Language :: Python
Classifier: Framework :: Odoo
Classifier: License :: OSI Approved :: GNU Lesser General Public License v3 (LGPLv3)
Requires-Python: ~=2.7
Requires-Dist: odoo (<9.0a,>=8.0a)
